orign_runtime/__init__.py
orign_runtime/stream/config.py
orign_runtime/stream/processors/base.py
orign_runtime/stream/processors/base_aio.py
orign_runtime/stream/processors/chat/hf/Dockerfile
orign_runtime/stream/processors/chat/hf/main.py
orign_runtime/stream/processors/chat/hf/model.py
orign_runtime/stream/processors/chat/hf-rt/config.py
orign_runtime/stream/processors/chat/hf-rt/main.py
orign_runtime/stream/processors/chat/hf-rt/model_factory.py
orign_runtime/stream/processors/chat/hf-rt/model_handler.py
orign_runtime/stream/processors/chat/hf-rt/models/Untitled.ipynb
orign_runtime/stream/processors/chat/hf-rt/models/Untitled1.ipynb
orign_runtime/stream/processors/chat/hf-rt/models/Untitled2.ipynb
orign_runtime/stream/processors/chat/hf-rt/models/Untitled3.ipynb
orign_runtime/stream/processors/chat/hf-rt/models/molmo.ipynb
orign_runtime/stream/processors/chat/hf-rt/models/molmo.py
orign_runtime/stream/processors/chat/hf-rt/models/molmo_batch_est.ipynb
orign_runtime/stream/processors/chat/hf-rt/models/molmo_batch_o1.ipynb
orign_runtime/stream/processors/chat/hf-rt/models/molmo_remote.ipynb
orign_runtime/stream/processors/chat/hf-rt/models/qwen2.ipynb
orign_runtime/stream/processors/chat/hf-rt/models/qwen2.py
orign_runtime/stream/processors/chat/hf-rt/models/qwen2_new.ipynb
orign_runtime/stream/processors/chat/hf-rt/models/qwen2_new2.ipynb
orign_runtime/stream/processors/chat/hf-rt/models/untitled.txt
orign_runtime/stream/processors/chat/hf-rt/seq.py
orign_runtime/stream/processors/chat/hf-rt/util.py
orign_runtime/stream/processors/chat/litellm/Dockerfile
orign_runtime/stream/processors/chat/litellm/main.py
orign_runtime/stream/processors/chat/vllm/Dockerfile
orign_runtime/stream/processors/chat/vllm/Dockerfile.old
orign_runtime/stream/processors/chat/vllm/fmt.py
orign_runtime/stream/processors/chat/vllm/main.py
orign_runtime/stream/processors/chat/vllm/qwen_vision.py
orign_runtime/stream/processors/completion/Dockerfile
orign_runtime-0.1.16.dist-info/LICENSE
orign_runtime-0.1.16.dist-info/METADATA
orign_runtime-0.1.16.dist-info/WHEEL
orign_runtime-0.1.16.dist-info/RECORD
